Metadata-Version: 2.1
Name: gimp-qrcode
Version: 0.0.0
Summary: Create QR Codes inside GIMP 3.
Home-page: https://github.com/isman7/gimp-python-development/
Author: ibenito
Author-email: ismaelbenito@protonmail.com
License: GNU GPLv3
Platform: UNKNOWN
